django_smart_ratelimit/__init__.py
django_smart_ratelimit/apps.py
django_smart_ratelimit/auth_utils.py
django_smart_ratelimit/circuit_breaker.py
django_smart_ratelimit/circuit_breaker_state.py
django_smart_ratelimit/conf.py
django_smart_ratelimit/config.py
django_smart_ratelimit/configuration.py
django_smart_ratelimit/context.py
django_smart_ratelimit/decorator.py
django_smart_ratelimit/exceptions.py
django_smart_ratelimit/key_functions.py
django_smart_ratelimit/messages.py
django_smart_ratelimit/middleware.py
django_smart_ratelimit/performance.py
django_smart_ratelimit/plugins.py
django_smart_ratelimit/utils.py
django_smart_ratelimit/views.py
django_smart_ratelimit/algorithms/__init__.py
django_smart_ratelimit/algorithms/base.py
django_smart_ratelimit/algorithms/token_bucket.py
django_smart_ratelimit/backends/__init__.py
django_smart_ratelimit/backends/base.py
django_smart_ratelimit/backends/factory.py
django_smart_ratelimit/backends/memory.py
django_smart_ratelimit/backends/mongodb.py
django_smart_ratelimit/backends/multi.py
django_smart_ratelimit/backends/redis_backend.py
django_smart_ratelimit/backends/utils.py
django_smart_ratelimit/management/__init__.py
django_smart_ratelimit/management/commands/__init__.py
django_smart_ratelimit/management/commands/ratelimit_health.py
django_smart_ratelimit-1.0.3.dist-info/METADATA
django_smart_ratelimit-1.0.3.dist-info/WHEEL
django_smart_ratelimit-1.0.3.dist-info/licenses/LICENSE
django_smart_ratelimit-1.0.3.dist-info/RECORD
