Metadata-Version: 2.4
Name: django-smart-ratelimit
Version: 1.0.3
Summary: A flexible and efficient rate limiting library for Django applications
Project-URL: Homepage, https://github.com/YasserShkeir/django-smart-ratelimit
Project-URL: Documentation, https://django-smart-ratelimit.readthedocs.io
Project-URL: Repository, https://github.com/YasserShkeir/django-smart-ratelimit
Project-URL: Issues, https://github.com/YasserShkeir/django-smart-ratelimit/issues
Project-URL: Discussions, https://github.com/YasserShkeir/django-smart-ratelimit/discussions
Project-URL: Changelog, https://github.com/YasserShkeir/django-smart-ratelimit/blob/main/CHANGELOG.md
Author-email: Yasser Shkeir <shkeiryasser@gmail.com>
License-Expression: MIT
License-File: LICENSE
Keywords: decorator,django,middleware,rate-limiting,redis
Classifier: Development Status :: 5 - Production/Stable
Classifier: Framework :: Django
Classifier: Framework :: Django :: 3.2
Classifier: Framework :: Django :: 4.0
Classifier: Framework :: Django :: 4.1
Classifier: Framework :: Django :: 4.2
Classifier: Framework :: Django :: 5.0
Classifier: Framework :: Django :: 5.1
Classifier: Intended Audience :: Developers
Classifier: License :: OSI Approved :: MIT License
Classifier: Operating System :: OS Independent
Classifier: Programming Language :: Python
Classifier: Programming Language :: Python :: 3
Classifier: Programming Language :: Python :: 3.9
Classifier: Programming Language :: Python :: 3.10
Classifier: Programming Language :: Python :: 3.11
Classifier: Programming Language :: Python :: 3.12
Classifier: Programming Language :: Python :: 3.13
Classifier: Topic :: Internet :: WWW/HTTP
Classifier: Topic :: Internet :: WWW/HTTP :: Dynamic Content
Classifier: Topic :: Software Development :: Libraries :: Python Modules
Classifier: Topic :: System :: Systems Administration
Requires-Python: >=3.9
Requires-Dist: asgiref>=3.6.0
Requires-Dist: django>=3.2
Provides-Extra: all
Requires-Dist: hiredis>=2.0; extra == 'all'
Requires-Dist: pyjwt>=2.0; extra == 'all'
Requires-Dist: pymongo>=4.0; extra == 'all'
Requires-Dist: redis>=4.0; extra == 'all'
Provides-Extra: dev
Requires-Dist: bandit>=1.7; extra == 'dev'
Requires-Dist: black>=22.0; extra == 'dev'
Requires-Dist: build>=0.8; extra == 'dev'
Requires-Dist: bump2version>=1.0; extra == 'dev'
Requires-Dist: django-stubs>=4.0; extra == 'dev'
Requires-Dist: flake8-docstrings>=1.7; extra == 'dev'
Requires-Dist: flake8>=5.0; extra == 'dev'
Requires-Dist: isort>=5.0; extra == 'dev'
Requires-Dist: mypy>=1.0; extra == 'dev'
Requires-Dist: pre-commit>=2.20; extra == 'dev'
Requires-Dist: pyjwt>=2.0; extra == 'dev'
Requires-Dist: pytest-asyncio>=0.21; extra == 'dev'
Requires-Dist: pytest-cov>=4.0; extra == 'dev'
Requires-Dist: pytest-django>=4.5; extra == 'dev'
Requires-Dist: pytest-xdist>=3.0; extra == 'dev'
Requires-Dist: pytest>=7.0; extra == 'dev'
Requires-Dist: safety>=2.0; extra == 'dev'
Requires-Dist: tox>=4.0; extra == 'dev'
Requires-Dist: twine>=4.0; extra == 'dev'
Requires-Dist: types-redis>=4.0; extra == 'dev'
Provides-Extra: jwt
Requires-Dist: pyjwt>=2.0; extra == 'jwt'
Provides-Extra: mongodb
Requires-Dist: pymongo>=4.0; extra == 'mongodb'
Provides-Extra: redis
Requires-Dist: hiredis>=2.0; extra == 'redis'
Requires-Dist: redis>=4.0; extra == 'redis'
